{
    "key": "group_5b7c5dbd23bda",
    "title": "Homepage",
    "fields": [
        {
            "key": "field_5b64a6a694470",
            "label": "Headline",
            "name": "headline",
            "type": "wysiwyg",
            "instructions": "",
            "required": 0,
            "conditional_logic": 0,
            "wrapper": {
                "width": "",
                "class": "",
                "id": ""
            },
            "default_value": "",
            "toolbar": "full",
            "media_upload": 1,
            "tabs": "all",
            "delay": 0
        },
        {
            "key": "field_5bad0740786ed",
            "label": "Video Embed Code",
            "name": "video_embed_code",
            "type": "textarea",
            "instructions": "",
            "required": 0,
            "conditional_logic": 0,
            "wrapper": {
                "width": "",
                "class": "",
                "id": ""
            },
            "default_value": "",
            "placeholder": "",
            "maxlength": "",
            "rows": "",
            "new_lines": ""
        },
        {
            "key": "field_5b64a69f9446f",
            "label": "Video Embed",
            "name": "video_url",
            "type": "text",
            "instructions": "",
            "required": 0,
            "conditional_logic": 0,
            "wrapper": {
                "width": "",
                "class": "",
                "id": ""
            },
            "default_value": "",
            "placeholder": "",
            "prepend": "",
            "append": "",
            "formatting": "html",
            "maxlength": ""
        },
        {
            "key": "field_5c506e25e4cfb",
            "label": "Below Laptop Text",
            "name": "below_laptop_text",
            "type": "wysiwyg",
            "instructions": "",
            "required": 0,
            "conditional_logic": 0,
            "wrapper": {
                "width": "",
                "class": "",
                "id": ""
            },
            "default_value": "",
            "tabs": "all",
            "toolbar": "full",
            "media_upload": 1,
            "delay": 0
        },
        {
            "key": "field_5b64a6d094472",
            "label": "Website Owners Icon",
            "name": "website_owners_icon",
            "type": "text",
            "instructions": "",
            "required": 0,
            "conditional_logic": 0,
            "wrapper": {
                "width": "",
                "class": "",
                "id": ""
            },
            "default_value": "",
            "placeholder": "",
            "prepend": "",
            "append": "",
            "formatting": "html",
            "maxlength": ""
        },
        {
            "key": "field_5b64a6df94473",
            "label": "Website Owners Text",
            "name": "website_owners_text",
            "type": "wysiwyg",
            "instructions": "",
            "required": 0,
            "conditional_logic": 0,
            "wrapper": {
                "width": "",
                "class": "",
                "id": ""
            },
            "default_value": "",
            "toolbar": "full",
            "media_upload": 1,
            "tabs": "all",
            "delay": 0
        },
        {
            "key": "field_5b64a6e494474",
            "label": "Website Owners button link",
            "name": "website_owners_button_link",
            "type": "text",
            "instructions": "",
            "required": 0,
            "conditional_logic": 0,
            "wrapper": {
                "width": "",
                "class": "",
                "id": ""
            },
            "default_value": "",
            "placeholder": "",
            "prepend": "",
            "append": "",
            "formatting": "html",
            "maxlength": ""
        },
        {
            "key": "field_5b64a6ec94475",
            "label": "Website Owners Button text",
            "name": "website_owners_",
            "type": "text",
            "instructions": "",
            "required": 0,
            "conditional_logic": 0,
            "wrapper": {
                "width": "",
                "class": "",
                "id": ""
            },
            "default_value": "",
            "placeholder": "",
            "prepend": "",
            "append": "",
            "formatting": "html",
            "maxlength": ""
        },
        {
            "key": "field_5b64a83f38edc",
            "label": "Content Author Icon",
            "name": "author_icon",
            "type": "text",
            "instructions": "",
            "required": 0,
            "conditional_logic": 0,
            "wrapper": {
                "width": "",
                "class": "",
                "id": ""
            },
            "default_value": "",
            "placeholder": "",
            "prepend": "",
            "append": "",
            "formatting": "html",
            "maxlength": ""
        },
        {
            "key": "field_5b64a84e38edd",
            "label": "Content Author Text",
            "name": "author_text",
            "type": "wysiwyg",
            "instructions": "",
            "required": 0,
            "conditional_logic": 0,
            "wrapper": {
                "width": "",
                "class": "",
                "id": ""
            },
            "default_value": "",
            "toolbar": "full",
            "media_upload": 1,
            "tabs": "all",
            "delay": 0
        },
        {
            "key": "field_5b64a85f38ede",
            "label": "Content Author button link",
            "name": "author_button_link",
            "type": "text",
            "instructions": "",
            "required": 0,
            "conditional_logic": 0,
            "wrapper": {
                "width": "",
                "class": "",
                "id": ""
            },
            "default_value": "",
            "placeholder": "",
            "prepend": "",
            "append": "",
            "formatting": "html",
            "maxlength": ""
        },
        {
            "key": "field_5b64a86e38edf",
            "label": "Content Author Button text",
            "name": "author_button_text",
            "type": "text",
            "instructions": "",
            "required": 0,
            "conditional_logic": 0,
            "wrapper": {
                "width": "",
                "class": "",
                "id": ""
            },
            "default_value": "",
            "placeholder": "",
            "prepend": "",
            "append": "",
            "formatting": "html",
            "maxlength": ""
        }
    ],
    "location": [
        [
            {
                "param": "page",
                "operator": "==",
                "value": "615"
            }
        ],
        [
            {
                "param": "page_template",
                "operator": "==",
                "value": "page-linkable-home.php"
            }
        ]
    ],
    "menu_order": 0,
    "position": "normal",
    "style": "seamless",
    "label_placement": "top",
    "instruction_placement": "label",
    "hide_on_screen": [
        "the_content"
    ],
    "active": 1,
    "description": "",
    "modified": 1594849278
}